tts/__init__.py
tts/tts.py
TTSUG-0.1.0.dist-info/LICENSE
TTSUG-0.1.0.dist-info/METADATA
TTSUG-0.1.0.dist-info/WHEEL
TTSUG-0.1.0.dist-info/top_level.txt
TTSUG-0.1.0.dist-info/RECORD
