Metadata-Version: 2.1
Name: TTSUG
Version: 0.1.0
Summary: A Python package for converting the text to speech
Home-page: https://github.com/swadeshrd/tts
Author: Swadesh Ranjan Dash
Author-email: swadesh5dash@gmail.com
License: MIT
Platform: UNKNOWN
Classifier: Programming Language :: Python :: 3
Classifier: License :: OSI Approved :: MIT License
Classifier: Operating System :: OS Independent
License-File: LICENSE
Requires-Dist: requests
